[
  {
    "idx": 0,
    "镜头": "镜头1",
    "角色": "沈念旁白",
    "情绪": "serious",
    "钩子": "hook",
    "文本": "三只小妖，同时回了头。死猫的血，还挂在覆鳞那张嘴上。",
    "时长": 4.36,
    "start": 0.0,
    "end": 4.36,
    "gap_after": 0.6,
    "line_wav": "line_00.wav",
    "占位": true
  },
  {
    "idx": 1,
    "镜头": "镜头2",
    "角色": "鳞片妖",
    "情绪": "neutral",
    "钩子": "",
    "文本": "哪来的废妃，倒会说大话。",
    "时长": 2.712,
    "start": 4.96,
    "end": 7.672,
    "gap_after": 0.4,
    "line_wav": "line_01.wav",
    "占位": true
  },
  {
    "idx": 2,
    "镜头": "镜头3",
    "角色": "枯枝指妖",
    "情绪": "serious",
    "钩子": "",
    "文本": "退租？先把你这身肉，给我们添个夜宵！",
    "时长": 2.967,
    "start": 8.072,
    "end": 11.039,
    "gap_after": 0.4,
    "line_wav": "line_02.wav",
    "占位": true
  },
  {
    "idx": 3,
    "镜头": "镜头4",
    "角色": "沈念旁白",
    "情绪": "serious",
    "钩子": "",
    "文本": "我没接话。我在看。三只妖成品字站开，背后是老槐，退路只在我身侧那道矮墙。",
    "时长": 6.116,
    "start": 11.439,
    "end": 17.556,
    "gap_after": 0.4,
    "line_wav": "line_03.wav",
    "占位": true
  },
  {
    "idx": 4,
    "镜头": "镜头5",
    "角色": "沈念旁白",
    "情绪": "neutral",
    "钩子": "hook",
    "文本": "能打，但不能拖。我身上只有潜行，蛮力借不出来。硬拼三只小妖，撑不过十息。",
    "时长": 6.055,
    "start": 17.956,
    "end": 24.01,
    "gap_after": 0.6,
    "line_wav": "line_04.wav",
    "占位": true
  },
  {
    "idx": 5,
    "镜头": "镜头6",
    "角色": "沈念旁白",
    "情绪": "neutral",
    "钩子": "",
    "文本": "那就不拼。",
    "时长": 1.259,
    "start": 24.61,
    "end": 25.869,
    "gap_after": 0.4,
    "line_wav": "line_05.wav",
    "占位": true
  },
  {
    "idx": 6,
    "镜头": "镜头7",
    "角色": "沈念旁白",
    "情绪": "neutral",
    "钩子": "",
    "文本": "我垂了垂眼，身形在树影里淡下去三分。裂口那只最先扑来，锯齿大张，是冲着我的喉咙来的。",
    "时长": 8.0,
    "start": 26.269,
    "end": 34.269,
    "gap_after": 0.4,
    "line_wav": "line_06.wav",
    "占位": true
  },
  {
    "idx": 7,
    "镜头": "镜头8",
    "角色": "沈念旁白",
    "情绪": "serious",
    "钩子": "",
    "文本": "我没退，反而贴上去。潜行收没了脚步，它扑了个空，整个脖子探了出来。",
    "时长": 5.571,
    "start": 34.669,
    "end": 40.24,
    "gap_after": 0.4,
    "line_wav": "line_07.wav",
    "占位": true
  },
  {
    "idx": 8,
    "镜头": "镜头9",
    "角色": "沈念旁白",
    "情绪": "neutral",
    "钩子": "",
    "文本": "我绕到它颈后，五指扣住咽喉，借它自己的冲势，往老槐树干上一带。",
    "时长": 5.269,
    "start": 40.64,
    "end": 45.909,
    "gap_after": 0.4,
    "line_wav": "line_08.wav",
    "占位": true
  },
  {
    "idx": 9,
    "镜头": "镜头10",
    "角色": "裂口妖",
    "情绪": "sad",
    "钩子": "",
    "文本": "啊——",
    "时长": 1.15,
    "start": 46.309,
    "end": 47.459,
    "gap_after": 0.4,
    "line_wav": "line_09.wav",
    "占位": true
  },
  {
    "idx": 10,
    "镜头": "镜头11",
    "角色": "沈念旁白",
    "情绪": "serious",
    "钩子": "climax",
    "文本": "咚。锯齿崩落两排。",
    "时长": 2.296,
    "start": 47.859,
    "end": 50.155,
    "gap_after": 0.7,
    "line_wav": "line_10.wav",
    "占位": true
  },
  {
    "idx": 11,
    "镜头": "镜头12",
    "角色": "沈念",
    "情绪": "serious",
    "钩子": "",
    "文本": "炼。",
    "时长": 1.15,
    "start": 50.855,
    "end": 52.005,
    "gap_after": 0.4,
    "line_wav": "line_11.wav",
    "占位": true
  },
  {
    "idx": 12,
    "镜头": "镜头13",
    "角色": "系统机械音",
    "情绪": "neutral",
    "钩子": "",
    "文本": "检测到妖躯。，是否炼化？",
    "时长": 2.61,
    "start": 52.405,
    "end": 55.015,
    "gap_after": 0.4,
    "line_wav": "line_12.wav",
    "占位": true
  },
  {
    "idx": 13,
    "镜头": "镜头14",
    "角色": "沈念",
    "情绪": "serious",
    "钩子": "",
    "文本": "是。",
    "时长": 1.15,
    "start": 55.415,
    "end": 56.565,
    "gap_after": 0.4,
    "line_wav": "line_13.wav",
    "占位": true
  },
  {
    "idx": 14,
    "镜头": "镜头15",
    "角色": "沈念旁白",
    "情绪": "neutral",
    "钩子": "",
    "文本": "黑烟从那张裂口里翻涌出来，顺着我的指缝钻进血脉。脑中炸开一片图景——它能学人声，能仿人言。",
    "时长": 8.0,
    "start": 56.965,
    "end": 64.965,
    "gap_after": 0.4,
    "line_wav": "line_14.wav",
    "占位": true
  },
  {
    "idx": 15,
    "镜头": "镜头16",
    "角色": "系统机械音",
    "情绪": "neutral",
    "钩子": "hook",
    "文本": "噬妖夺能。，可得：摄声·仿言。",
    "时长": 2.952,
    "start": 65.365,
    "end": 68.317,
    "gap_after": 0.6,
    "line_wav": "line_15.wav",
    "占位": true
  },
  {
    "idx": 16,
    "镜头": "镜头17",
    "角色": "沈念旁白",
    "情绪": "serious",
    "钩子": "",
    "文本": "没用。仿言是阴的，是骗的。于我眼下立威，无益。",
    "时长": 3.753,
    "start": 68.917,
    "end": 72.67,
    "gap_after": 0.4,
    "line_wav": "line_16.wav",
    "占位": true
  },
  {
    "idx": 17,
    "镜头": "镜头18",
    "角色": "沈念旁白",
    "情绪": "neutral",
    "钩子": "",
    "文本": "可那两只，已经扑上来了。覆鳞低吼，枯枝指从侧后包抄，倒刺在月下泛着冷光。",
    "时长": 6.116,
    "start": 73.07,
    "end": 79.186,
    "gap_after": 0.4,
    "line_wav": "line_17.wav",
    "占位": true
  },
  {
    "idx": 18,
    "镜头": "镜头19",
    "角色": "沈念旁白",
    "情绪": "neutral",
    "钩子": "hook",
    "文本": "我要的，从来只有一样东西，能让我在这冷宫里立住脚——，扛得住打。",
    "时长": 6.508,
    "start": 79.586,
    "end": 86.094,
    "gap_after": 0.6,
    "line_wav": "line_18.wav",
    "占位": true
  },
  {
    "idx": 19,
    "镜头": "镜头20",
    "角色": "沈念旁白",
    "情绪": "serious",
    "钩子": "",
    "文本": "覆鳞撞上来的刹那，我没有躲。我侧身让过倒刺，反手按上它的脊背。",
    "时长": 5.269,
    "start": 86.694,
    "end": 91.963,
    "gap_after": 0.4,
    "line_wav": "line_19.wav",
    "占位": true
  },
  {
    "idx": 20,
    "镜头": "镜头21",
    "角色": "沈念",
    "情绪": "neutral",
    "钩子": "",
    "文本": "就是你了。",
    "时长": 1.259,
    "start": 92.363,
    "end": 93.622,
    "gap_after": 0.4,
    "line_wav": "line_20.wav",
    "占位": true
  },
  {
    "idx": 21,
    "镜头": "镜头22",
    "角色": "系统机械音",
    "情绪": "neutral",
    "钩子": "",
    "文本": "检测到妖躯。覆鳞妖。，鳞甲硬防御。",
    "时长": 3.619,
    "start": 94.022,
    "end": 97.641,
    "gap_after": 0.4,
    "line_wav": "line_21.wav",
    "占位": true
  },
  {
    "idx": 22,
    "镜头": "镜头23",
    "角色": "沈念",
    "情绪": "serious",
    "钩子": "climax",
    "文本": "炼。",
    "时长": 1.15,
    "start": 98.041,
    "end": 99.191,
    "gap_after": 0.7,
    "line_wav": "line_22.wav",
    "占位": true
  },
  {
    "idx": 23,
    "镜头": "镜头24",
    "角色": "沈念旁白",
    "情绪": "sad",
    "钩子": "",
    "文本": "这一回，我吃得贪了。裂口妖的摄声还没消化，覆鳞的鳞甲又汹涌灌入。",
    "时长": 5.451,
    "start": 99.891,
    "end": 105.342,
    "gap_after": 0.4,
    "line_wav": "line_23.wav",
    "占位": true
  },
  {
    "idx": 24,
    "镜头": "镜头25",
    "角色": "沈念旁白",
    "情绪": "sad",
    "钩子": "hook",
    "文本": "两股妖气在我体内对撞，胸口像被塞进一团烧红的炭，烧得骨血都在响。",
    "时长": 5.513,
    "start": 105.742,
    "end": 111.254,
    "gap_after": 0.6,
    "line_wav": "line_24.wav",
    "占位": true
  },
  {
    "idx": 25,
    "镜头": "镜头26",
    "角色": "系统机械音",
    "情绪": "neutral",
    "钩子": "",
    "文本": "同源相斥。，血脉过载。",
    "时长": 1.695,
    "start": 111.854,
    "end": 113.549,
    "gap_after": 0.4,
    "line_wav": "line_25.wav",
    "占位": true
  },
  {
    "idx": 26,
    "镜头": "镜头27",
    "角色": "系统机械音",
    "情绪": "neutral",
    "钩子": "",
    "文本": "警告：贪噬反噬——",
    "时长": 1.15,
    "start": 113.949,
    "end": 115.099,
    "gap_after": 0.4,
    "line_wav": "line_26.wav",
    "占位": true
  },
  {
    "idx": 27,
    "镜头": "镜头28",
    "角色": "沈念旁白",
    "情绪": "neutral",
    "钩子": "end",
    "文本": "我眼前，骤然红了。不是血，是整座皇城，都隔着一层血纱，变成了该吞下去的肉。",
    "时长": 8.0,
    "start": 115.499,
    "end": 123.499,
    "gap_after": 0.0,
    "line_wav": "line_27.wav",
    "占位": true
  }
]